{"status":1,"msg":"","id":"1D891124-908E-4923-BC41-AD90B32A2560","entityLabel":"实体对象","keyPrefix":"01I","entityApiName":"Entity","record":{"Name":"ApplicationCenter","CreatedOn":"2023-06-04 16:24:53","ModifiedOn":"2023-06-04 16:24:53","DisplayName":"工作台应用","Description":"","ObjectTypeCode":100060,"EntityCode":"03a","BaseTableName":"ApplicationCenterBase","IsPublished":true,"ParentFolderId":{"Id":"b6c7d71b-8880-4cf0-8936-051366eb5e7e","Name":"","objectTypeCode":"0","sobjectType":"0"},"IsCustomEntity":true,"IsChildEntity":true,"MasterEntityId":{"Id":"eba2073d-7317-4fba-b950-3db5f41d3249","Name":"应用分组","objectTypeCode":"100000","sobjectType":"100000"}},"context":{"picklistValuesMap":{},"globalValueProviders":[{"type":"$Record","values":{"objectMetadata":{"Entity":{"_nameField":"DisplayName","_entityLabel":"实体对象","_keyPrefix":"01I"}}}}],"appContextUser":{"userId":"2ec00cf2-a484-4136-8fef-e2a2719c5ed6","name":"jackliu45"}},"entity":{"ObjectTypeCode":100000,"EntityType":"01I"}}
