{"status":"1","msg":"","listData":[{"FullName":"胡争云","UserName":"2002","SystemUserId":"b05295c8-680c-448a-a220-66e212a99629","EmployeeNo":"2002","BusinessUnitId":"","BusinessUnitIdName":"","MobilePhone":"","EMailAddress":"","WorkStatus":"","JobTitle":"","OrganizationName":"南京市第二医院","PhotoUrl":"/apps/CommandProcessor.ashx?cmd=show.emp.avatar&id=b05295c8-680c-448a-a220-66e212a99629"},{"FullName":"闵露露","UserName":"0981","SystemUserId":"76715375-f075-4636-a917-29b014d9c2b4","EmployeeNo":"0981","BusinessUnitId":"a97909d8-d097-4ae0-92e7-e1c5aa790400","BusinessUnitIdName":"组织人事科","MobilePhone":"13851991403","EMailAddress":"","WorkStatus":"","JobTitle":"","OrganizationName":"南京市第二医院","PhotoUrl":"/apps/CommandProcessor.ashx?cmd=show.emp.avatar&id=76715375-f075-4636-a917-29b014d9c2b4"},{"FullName":"罗逸宁","UserName":"0810","SystemUserId":"7b94b238-6e74-4076-aa37-1ea077548ad7","EmployeeNo":"0810","BusinessUnitId":"cf141ed4-d858-4554-bc7c-13cbf33dfd1c","BusinessUnitIdName":"招标采购中心","MobilePhone":"13801582980","EMailAddress":"","WorkStatus":"","JobTitle":"","OrganizationName":"南京市第二医院","PhotoUrl":"/apps/CommandProcessor.ashx?cmd=show.emp.avatar&id=7b94b238-6e74-4076-aa37-1ea077548ad7"},{"FullName":"刘修齐","UserName":"2016100","SystemUserId":"e6494491-5483-4e7d-8dbb-3fe2b38c792f","EmployeeNo":"2016100","BusinessUnitId":"fc6b89a8-c775-4b87-a010-3a80e9fbdeaa","BusinessUnitIdName":"财务科（资产管理办公室）","MobilePhone":"18762281188","EMailAddress":"","WorkStatus":"","JobTitle":"","OrganizationName":"南京市第二医院","PhotoUrl":"/apps/CommandProcessor.ashx?cmd=show.emp.avatar&id=e6494491-5483-4e7d-8dbb-3fe2b38c792f"},{"FullName":"李丽","UserName":"1188","SystemUserId":"43a63f2d-5e56-42ce-9d38-e7f0aabf82f4","EmployeeNo":"1188","BusinessUnitId":"e8d0de5b-3c29-42b5-9b2e-a8198e29a692","BusinessUnitIdName":"超声医学科","MobilePhone":"18115602868","EMailAddress":"","WorkStatus":"","JobTitle":"","OrganizationName":"南京市第二医院","PhotoUrl":"/apps/CommandProcessor.ashx?cmd=show.emp.avatar&id=43a63f2d-5e56-42ce-9d38-e7f0aabf82f4"},{"FullName":"史云婕","UserName":"201375","SystemUserId":"25178944-dc5e-4a5d-adea-96f6a0d30e16","EmployeeNo":"201375","BusinessUnitId":"a2962eaf-9b10-4d14-afad-69d197c2c8cd","BusinessUnitIdName":"肝病一科","MobilePhone":"15850709732","EMailAddress":"","WorkStatus":"","JobTitle":"","OrganizationName":"南京市第二医院","PhotoUrl":"/apps/CommandProcessor.ashx?cmd=show.emp.avatar&id=25178944-dc5e-4a5d-adea-96f6a0d30e16"},{"FullName":"王晓燕","UserName":"1015","SystemUserId":"0fb2254e-e625-466f-aca4-34138c388341","EmployeeNo":"1015","BusinessUnitId":"a2962eaf-9b10-4d14-afad-69d197c2c8cd","BusinessUnitIdName":"肝病一科","MobilePhone":"15996207169","EMailAddress":"","WorkStatus":"","JobTitle":"","OrganizationName":"南京市第二医院","PhotoUrl":"/apps/CommandProcessor.ashx?cmd=show.emp.avatar&id=0fb2254e-e625-466f-aca4-34138c388341"},{"FullName":"李菁1","UserName":"0399","SystemUserId":"8719816d-c33c-4569-8c24-003909e74ffa","EmployeeNo":"0399","BusinessUnitId":"d04474d2-e358-4b38-bb1a-ba933f5bd904","BusinessUnitIdName":"综合外科","MobilePhone":"13914757432","EMailAddress":"","WorkStatus":"","JobTitle":"","OrganizationName":"南京市第二医院","PhotoUrl":"/apps/CommandProcessor.ashx?cmd=show.emp.avatar&id=8719816d-c33c-4569-8c24-003909e74ffa"},{"FullName":"范梅","UserName":"201761","SystemUserId":"670b6590-2aa7-4972-99eb-75745a038df6","EmployeeNo":"201761","BusinessUnitId":"a2962eaf-9b10-4d14-afad-69d197c2c8cd","BusinessUnitIdName":"肝病一科","MobilePhone":"19805148545","EMailAddress":"","WorkStatus":"","JobTitle":"","OrganizationName":"南京市第二医院","PhotoUrl":"/apps/CommandProcessor.ashx?cmd=show.emp.avatar&id=670b6590-2aa7-4972-99eb-75745a038df6"},{"FullName":"陈爱玲","UserName":"201392","SystemUserId":"a5c82235-5682-4a92-b82b-87d213b0ffc6","EmployeeNo":"201392","BusinessUnitId":"84094722-14d5-4fc1-85a9-c29370a3df61","BusinessUnitIdName":"产房、新生儿科","MobilePhone":"18512526797","EMailAddress":"","WorkStatus":"","JobTitle":"","OrganizationName":"南京市第二医院","PhotoUrl":"/apps/CommandProcessor.ashx?cmd=show.emp.avatar&id=a5c82235-5682-4a92-b82b-87d213b0ffc6"},{"FullName":"徐元龙","UserName":"201802","SystemUserId":"d454fb6d-f08c-454a-990f-735fafdac8c8","EmployeeNo":"201802","BusinessUnitId":"53eecec7-868e-425e-9277-6e6da8b7e5f8","BusinessUnitIdName":"结核四科","MobilePhone":"13915979143","EMailAddress":"","WorkStatus":"","JobTitle":"","OrganizationName":"南京市第二医院","PhotoUrl":"/apps/CommandProcessor.ashx?cmd=show.emp.avatar&id=d454fb6d-f08c-454a-990f-735fafdac8c8"},{"FullName":"徐匡义","UserName":"2016101","SystemUserId":"8a3310c4-5e9a-4e2e-a2b1-96b9914be2e4","EmployeeNo":"2016101","BusinessUnitId":"3bae7ff3-a22f-4f4d-944d-e9e6e678de0b","BusinessUnitIdName":"院长办公室（外事办、法制办）","MobilePhone":"13776083856","EMailAddress":"","WorkStatus":"","JobTitle":"","OrganizationName":"南京市第二医院","PhotoUrl":"/apps/CommandProcessor.ashx?cmd=show.emp.avatar&id=8a3310c4-5e9a-4e2e-a2b1-96b9914be2e4"}],"totalRowCount":22,"rowsPerPage":22,"page":1}
